[
  {
    "country": "🇨🇳 China (Mainland)",
    "arrival_city": "Beijing (PEK)",
    "arrival_airport": "PEK",
    "flight_number": "CX334",
    "departure_time": "07:25",
    "arrival_time": "10:45",
    "duration": "3h 20m",
    "departure_band": "Morning",
    "arrival_next_day": false
  },
  {
    "country": "🇨🇳 China (Mainland)",
    "arrival_city": "Beijing (PEK)",
    "arrival_airport": "PEK",
    "flight_number": "CX390",
    "departure_time": "09:00",
    "arrival_time": "12:25",
    "duration": "3h 25m",
    "departure_band": "Morning",
    "arrival_next_day": false
  },
  {
    "country": "🇨🇳 China (Mainland)",
    "arrival_city": "Beijing (PEK)",
    "arrival_airport": "PEK",
    "flight_number": "CX332",
    "departure_time": "12:00",
    "arrival_time": "15:25",
    "duration": "3h 25m",
    "departure_band": "Afternoon",
    "arrival_next_day": false
  },
  {
    "country": "🇨🇳 China (Mainland)",
    "arrival_city": "Beijing (PEK)",
    "arrival_airport": "PEK",
    "flight_number": "CX392",
    "departure_time": "12:55",
    "arrival_time": "17:25",
    "duration": "4h 30m",
    "departure_band": "Afternoon",
    "arrival_next_day": false
  },
  {
    "country": "🇨🇳 China (Mainland)",
    "arrival_city": "Beijing (PEK)",
    "arrival_airport": "PEK",
    "flight_number": "CX336",
    "departure_time": "15:00",
    "arrival_time": "18:25",
    "duration": "3h 25m",
    "departure_band": "Afternoon",
    "arrival_next_day": false
  },
  {
    "country": "🇨🇳 China (Mainland)",
    "arrival_city": "Beijing (PEK)",
    "arrival_airport": "PEK",
    "flight_number": "CX312",
    "departure_time": "17:00",
    "arrival_time": "20:25",
    "duration": "3h 25m",
    "departure_band": "Evening",
    "arrival_next_day": false
  },
  {
    "country": "🇨🇳 China (Mainland)",
    "arrival_city": "Beijing (PEK)",
    "arrival_airport": "PEK",
    "flight_number": "CX344",
    "departure_time": "19:00",
    "arrival_time": "22:25",
    "duration": "3h 25m",
    "departure_band": "Evening",
    "arrival_next_day": false
  },
  {
    "country": "🇨🇳 China (Mainland)",
    "arrival_city": "Beijing (PEK)",
    "arrival_airport": "PEK",
    "flight_number": "CX340",
    "departure_time": "21:55",
    "arrival_time": "01:25",
    "duration": "3h 30m",
    "departure_band": "Night",
    "arrival_next_day": true
  },
  {
    "country": "🇨🇳 China (Mainland)",
    "arrival_city": "Changsha (CSX)",
    "arrival_airport": "CSX",
    "flight_number": "CX330",
    "departure_time": "09:15",
    "arrival_time": "11:00",
    "duration": "1h 45m",
    "departure_band": "Morning",
    "arrival_next_day": false
  },
  {
    "country": "🇨🇳 China (Mainland)",
    "arrival_city": "Changsha (CSX)",
    "arrival_airport": "CSX",
    "flight_number": "CX314",
    "departure_time": "10:15",
    "arrival_time": "12:00",
    "duration": "1h 45m",
    "departure_band": "Morning",
    "arrival_next_day": false
  },
  {
    "country": "🇨🇳 China (Mainland)",
    "arrival_city": "Chengdu (TFU)",
    "arrival_airport": "TFU",
    "flight_number": "CX986",
    "departure_time": "10:00",
    "arrival_time": "12:35",
    "duration": "2h 35m",
    "departure_band": "Morning",
    "arrival_next_day": false
  },
  {
    "country": "🇨🇳 China (Mainland)",
    "arrival_city": "Chengdu (TFU)",
    "arrival_airport": "TFU",
    "flight_number": "CX916",
    "departure_time": "19:15",
    "arrival_time": "21:55",
    "duration": "2h 40m",
    "departure_band": "Evening",
    "arrival_next_day": false
  },
  {
    "country": "🇨🇳 China (Mainland)",
    "arrival_city": "Chongqing (CKG)",
    "arrival_airport": "CKG",
    "flight_number": "CX928",
    "departure_time": "13:35",
    "arrival_time": "16:10",
    "duration": "2h 35m",
    "departure_band": "Afternoon",
    "arrival_next_day": false
  },
  {
    "country": "🇨🇳 China (Mainland)",
    "arrival_city": "Fuzhou (FOC)",
    "arrival_airport": "FOC",
    "flight_number": "CX914",
    "departure_time": "08:30",
    "arrival_time": "10:15",
    "duration": "1h 45m",
    "departure_band": "Morning",
    "arrival_next_day": false
  },
  {
    "country": "🇨🇳 China (Mainland)",
    "arrival_city": "Fuzhou (FOC)",
    "arrival_airport": "FOC",
    "flight_number": "CX990",
    "departure_time": "17:40",
    "arrival_time": "19:25",
    "duration": "1h 45m",
    "departure_band": "Evening",
    "arrival_next_day": false
  },
  {
    "country": "🇨🇳 China (Mainland)",
    "arrival_city": "Guangzhou (CAN)",
    "arrival_airport": "CAN",
    "flight_number": "CX950",
    "departure_time": "01:15",
    "arrival_time": "02:20",
    "duration": "1h 05m",
    "departure_band": "Night",
    "arrival_next_day": false
  },
  {
    "country": "🇨🇳 China (Mainland)",
    "arrival_city": "Guangzhou (CAN)",
    "arrival_airport": "CAN",
    "flight_number": "CX982",
    "departure_time": "07:50",
    "arrival_time": "08:55",
    "duration": "1h 05m",
    "departure_band": "Morning",
    "arrival_next_day": false
  },
  {
    "country": "🇨🇳 China (Mainland)",
    "arrival_city": "Guangzhou (CAN)",
    "arrival_airport": "CAN",
    "flight_number": "CX988",
    "departure_time": "20:00",
    "arrival_time": "21:05",
    "duration": "1h 05m",
    "departure_band": "Evening",
    "arrival_next_day": false
  },
  {
    "country": "🇨🇳 China (Mainland)",
    "arrival_city": "Haikou (HAK)",
    "arrival_airport": "HAK",
    "flight_number": "CX310",
    "departure_time": "14:10",
    "arrival_time": "15:40",
    "duration": "1h 30m",
    "departure_band": "Afternoon",
    "arrival_next_day": false
  },
  {
    "country": "🇨🇳 China (Mainland)",
    "arrival_city": "Hangzhou (HGH)",
    "arrival_airport": "HGH",
    "flight_number": "CX958",
    "departure_time": "07:45",
    "arrival_time": "10:10",
    "duration": "2h 25m",
    "departure_band": "Morning",
    "arrival_next_day": false
  },
  {
    "country": "🇨🇳 China (Mainland)",
    "arrival_city": "Hangzhou (HGH)",
    "arrival_airport": "HGH",
    "flight_number": "CX960",
    "departure_time": "12:15",
    "arrival_time": "14:40",
    "duration": "2h 25m",
    "departure_band": "Afternoon",
    "arrival_next_day": false
  },
  {
    "country": "🇨🇳 China (Mainland)",
    "arrival_city": "Hangzhou (HGH)",
    "arrival_airport": "HGH",
    "flight_number": "CX962",
    "departure_time": "16:00",
    "arrival_time": "18:30",
    "duration": "2h 30m",
    "departure_band": "Afternoon",
    "arrival_next_day": false
  },
  {
    "country": "🇨🇳 China (Mainland)",
    "arrival_city": "Hangzhou (HGH)",
    "arrival_airport": "HGH",
    "flight_number": "CX964",
    "departure_time": "20:10",
    "arrival_time": "22:35",
    "duration": "2h 25m",
    "departure_band": "Evening",
    "arrival_next_day": false
  },
  {
    "country": "🇨🇳 China (Mainland)",
    "arrival_city": "Nanjing (NKG)",
    "arrival_airport": "NKG",
    "flight_number": "CX356",
    "departure_time": "10:25",
    "arrival_time": "13:00",
    "duration": "2h 35m",
    "departure_band": "Morning",
    "arrival_next_day": false
  },
  {
    "country": "🇨🇳 China (Mainland)",
    "arrival_city": "Nanjing (NKG)",
    "arrival_airport": "NKG",
    "flight_number": "CX304",
    "departure_time": "19:25",
    "arrival_time": "22:05",
    "duration": "2h 40m",
    "departure_band": "Evening",
    "arrival_next_day": false
  },
  {
    "country": "🇨🇳 China (Mainland)",
    "arrival_city": "Ningbo (NGB)",
    "arrival_airport": "NGB",
    "flight_number": "CX956",
    "departure_time": "11:00",
    "arrival_time": "13:20",
    "duration": "2h 20m",
    "departure_band": "Morning",
    "arrival_next_day": false
  },
  {
    "country": "🇨🇳 China (Mainland)",
    "arrival_city": "Qingdao (TAO)",
    "arrival_airport": "TAO",
    "flight_number": "CX954",
    "departure_time": "10:15",
    "arrival_time": "13:30",
    "duration": "3h 15m",
    "departure_band": "Morning",
    "arrival_next_day": false
  },
  {
    "country": "🇨🇳 China (Mainland)",
    "arrival_city": "Shanghai Pudong (PVG)",
    "arrival_airport": "PVG",
    "flight_number": "CX316",
    "departure_time": "08:10",
    "arrival_time": "11:05",
    "duration": "2h 55m",
    "departure_band": "Morning",
    "arrival_next_day": false
  },
  {
    "country": "🇨🇳 China (Mainland)",
    "arrival_city": "Shanghai Pudong (PVG)",
    "arrival_airport": "PVG",
    "flight_number": "CX368",
    "departure_time": "09:20",
    "arrival_time": "12:05",
    "duration": "2h 45m",
    "departure_band": "Morning",
    "arrival_next_day": false
  },
  {
    "country": "🇨🇳 China (Mainland)",
    "arrival_city": "Shanghai Pudong (PVG)",
    "arrival_airport": "PVG",
    "flight_number": "CX376",
    "departure_time": "10:25",
    "arrival_time": "13:15",
    "duration": "2h 50m",
    "departure_band": "Morning",
    "arrival_next_day": false
  },
  {
    "country": "🇨🇳 China (Mainland)",
    "arrival_city": "Shanghai Pudong (PVG)",
    "arrival_airport": "PVG",
    "flight_number": "CX360",
    "departure_time": "13:40",
    "arrival_time": "16:25",
    "duration": "2h 45m",
    "departure_band": "Afternoon",
    "arrival_next_day": false
  },
  {
    "country": "🇨🇳 China (Mainland)",
    "arrival_city": "Shanghai Pudong (PVG)",
    "arrival_airport": "PVG",
    "flight_number": "CX380",
    "departure_time": "15:00",
    "arrival_time": "17:50",
    "duration": "2h 50m",
    "departure_band": "Afternoon",
    "arrival_next_day": false
  },
  {
    "country": "🇨🇳 China (Mainland)",
    "arrival_city": "Shanghai Pudong (PVG)",
    "arrival_airport": "PVG",
    "flight_number": "CX364",
    "departure_time": "17:25",
    "arrival_time": "20:15",
    "duration": "2h 50m",
    "departure_band": "Evening",
    "arrival_next_day": false
  },
  {
    "country": "🇨🇳 China (Mainland)",
    "arrival_city": "Shanghai Pudong (PVG)",
    "arrival_airport": "PVG",
    "flight_number": "CX362",
    "departure_time": "19:20",
    "arrival_time": "22:10",
    "duration": "2h 50m",
    "departure_band": "Evening",
    "arrival_next_day": false
  },
  {
    "country": "🇨🇳 China (Mainland)",
    "arrival_city": "Shanghai Pudong (PVG)",
    "arrival_airport": "PVG",
    "flight_number": "CX302",
    "departure_time": "21:05",
    "arrival_time": "23:55",
    "duration": "2h 50m",
    "departure_band": "Night",
    "arrival_next_day": false
  },
  {
    "country": "🇨🇳 China (Mainland)",
    "arrival_city": "Shanghai Hongqiao (SHA)",
    "arrival_airport": "SHA",
    "flight_number": "CX342",
    "departure_time": "09:35",
    "arrival_time": "12:05",
    "duration": "2h 30m",
    "departure_band": "Morning",
    "arrival_next_day": false
  },
  {
    "country": "🇨🇳 China (Mainland)",
    "arrival_city": "Shanghai Hongqiao (SHA)",
    "arrival_airport": "SHA",
    "flight_number": "CX328",
    "departure_time": "18:25",
    "arrival_time": "20:55",
    "duration": "2h 30m",
    "departure_band": "Evening",
    "arrival_next_day": false
  },
  {
    "country": "🇨🇳 China (Mainland)",
    "arrival_city": "Urumqi (URC)",
    "arrival_airport": "URC",
    "flight_number": "CX998",
    "departure_time": "01:15",
    "arrival_time": "07:00",
    "duration": "5h 45m",
    "departure_band": "Night",
    "arrival_next_day": false
  },
  {
    "country": "🇨🇳 China (Mainland)",
    "arrival_city": "Wenzhou (WNZ)",
    "arrival_airport": "WNZ",
    "flight_number": "CX384",
    "departure_time": "08:30",
    "arrival_time": "10:40",
    "duration": "2h 10m",
    "departure_band": "Morning",
    "arrival_next_day": false
  },
  {
    "country": "🇨🇳 China (Mainland)",
    "arrival_city": "Wenzhou (WNZ)",
    "arrival_airport": "WNZ",
    "flight_number": "CX396",
    "departure_time": "17:00",
    "arrival_time": "19:05",
    "duration": "2h 05m",
    "departure_band": "Evening",
    "arrival_next_day": false
  },
  {
    "country": "🇨🇳 China (Mainland)",
    "arrival_city": "Wuhan (WUH)",
    "arrival_airport": "WUH",
    "flight_number": "CX936",
    "departure_time": "08:15",
    "arrival_time": "10:20",
    "duration": "2h 05m",
    "departure_band": "Morning",
    "arrival_next_day": false
  },
  {
    "country": "🇨🇳 China (Mainland)",
    "arrival_city": "Wuhan (WUH)",
    "arrival_airport": "WUH",
    "flight_number": "CX938",
    "departure_time": "17:35",
    "arrival_time": "19:40",
    "duration": "2h 05m",
    "departure_band": "Evening",
    "arrival_next_day": false
  },
  {
    "country": "🇨🇳 China (Mainland)",
    "arrival_city": "Xi’an (XIY)",
    "arrival_airport": "XIY",
    "flight_number": "CX946",
    "departure_time": "11:10",
    "arrival_time": "14:30",
    "duration": "3h 20m",
    "departure_band": "Morning",
    "arrival_next_day": false
  },
  {
    "country": "🇨🇳 China (Mainland)",
    "arrival_city": "Xiamen (XMN)",
    "arrival_airport": "XMN",
    "flight_number": "CX970",
    "departure_time": "09:30",
    "arrival_time": "11:05",
    "duration": "1h 35m",
    "departure_band": "Morning",
    "arrival_next_day": false
  },
  {
    "country": "🇨🇳 China (Mainland)",
    "arrival_city": "Xiamen (XMN)",
    "arrival_airport": "XMN",
    "flight_number": "CX978",
    "departure_time": "17:45",
    "arrival_time": "19:25",
    "duration": "1h 40m",
    "departure_band": "Evening",
    "arrival_next_day": false
  },
  {
    "country": "🇨🇳 China (Mainland)",
    "arrival_city": "Zhengzhou (CGO)",
    "arrival_airport": "CGO",
    "flight_number": "CX952",
    "departure_time": "12:45",
    "arrival_time": "15:20",
    "duration": "2h 35m",
    "departure_band": "Afternoon",
    "arrival_next_day": false
  },
  {
    "country": "🇯🇵 Japan",
    "arrival_city": "Tokyo Narita (NRT)",
    "arrival_airport": "NRT",
    "flight_number": "CX524",
    "departure_time": "01:20",
    "arrival_time": "06:50",
    "duration": "5h 30m",
    "departure_band": "Night",
    "arrival_next_day": false
  },
  {
    "country": "🇯🇵 Japan",
    "arrival_city": "Tokyo Narita (NRT)",
    "arrival_airport": "NRT",
    "flight_number": "CX526",
    "departure_time": "08:15",
    "arrival_time": "13:40",
    "duration": "5h 25m",
    "departure_band": "Morning",
    "arrival_next_day": false
  },
  {
    "country": "🇯🇵 Japan",
    "arrival_city": "Tokyo Narita (NRT)",
    "arrival_airport": "NRT",
    "flight_number": "CX504",
    "departure_time": "09:05",
    "arrival_time": "14:30",
    "duration": "5h 25m",
    "departure_band": "Morning",
    "arrival_next_day": false
  },
  {
    "country": "🇯🇵 Japan",
    "arrival_city": "Tokyo Narita (NRT)",
    "arrival_airport": "NRT",
    "flight_number": "CX520",
    "departure_time": "10:40",
    "arrival_time": "16:05",
    "duration": "5h 25m",
    "departure_band": "Morning",
    "arrival_next_day": false
  },
  {
    "country": "🇯🇵 Japan",
    "arrival_city": "Tokyo Narita (NRT)",
    "arrival_airport": "NRT",
    "flight_number": "CX500",
    "departure_time": "15:20",
    "arrival_time": "20:50",
    "duration": "5h 30m",
    "departure_band": "Afternoon",
    "arrival_next_day": false
  },
  {
    "country": "🇯🇵 Japan",
    "arrival_city": "Tokyo Haneda (HND)",
    "arrival_airport": "HND",
    "flight_number": "CX548",
    "departure_time": "08:40",
    "arrival_time": "13:55",
    "duration": "5h 15m",
    "departure_band": "Morning",
    "arrival_next_day": false
  },
  {
    "country": "🇯🇵 Japan",
    "arrival_city": "Tokyo Haneda (HND)",
    "arrival_airport": "HND",
    "flight_number": "CX542",
    "departure_time": "16:20",
    "arrival_time": "21:35",
    "duration": "5h 15m",
    "departure_band": "Afternoon",
    "arrival_next_day": false
  },
  {
    "country": "🇯🇵 Japan",
    "arrival_city": "Osaka (KIX)",
    "arrival_airport": "KIX",
    "flight_number": "CX566",
    "departure_time": "01:55",
    "arrival_time": "06:40",
    "duration": "4h 45m",
    "departure_band": "Night",
    "arrival_next_day": false
  },
  {
    "country": "🇯🇵 Japan",
    "arrival_city": "Osaka (KIX)",
    "arrival_airport": "KIX",
    "flight_number": "CX596",
    "departure_time": "08:10",
    "arrival_time": "12:55",
    "duration": "4h 45m",
    "departure_band": "Morning",
    "arrival_next_day": false
  },
  {
    "country": "🇯🇵 Japan",
    "arrival_city": "Osaka (KIX)",
    "arrival_airport": "KIX",
    "flight_number": "CX506",
    "departure_time": "10:25",
    "arrival_time": "15:10",
    "duration": "4h 45m",
    "departure_band": "Morning",
    "arrival_next_day": false
  },
  {
    "country": "🇯🇵 Japan",
    "arrival_city": "Osaka (KIX)",
    "arrival_airport": "KIX",
    "flight_number": "CX598",
    "departure_time": "13:20",
    "arrival_time": "18:05",
    "duration": "4h 45m",
    "departure_band": "Afternoon",
    "arrival_next_day": false
  },
  {
    "country": "🇯🇵 Japan",
    "arrival_city": "Osaka (KIX)",
    "arrival_airport": "KIX",
    "flight_number": "CX502",
    "departure_time": "16:30",
    "arrival_time": "21:15",
    "duration": "4h 45m",
    "departure_band": "Afternoon",
    "arrival_next_day": false
  },
  {
    "country": "🇯🇵 Japan",
    "arrival_city": "Nagoya (NGO)",
    "arrival_airport": "NGO",
    "flight_number": "CX536",
    "departure_time": "10:10",
    "arrival_time": "15:05",
    "duration": "4h 55m",
    "departure_band": "Morning",
    "arrival_next_day": false
  },
  {
    "country": "🇯🇵 Japan",
    "arrival_city": "Nagoya (NGO)",
    "arrival_airport": "NGO",
    "flight_number": "CX532",
    "departure_time": "16:15",
    "arrival_time": "21:15",
    "duration": "5h 00m",
    "departure_band": "Afternoon",
    "arrival_next_day": false
  },
  {
    "country": "🇯🇵 Japan",
    "arrival_city": "Fukuoka (FUK)",
    "arrival_airport": "FUK",
    "flight_number": "CX512",
    "departure_time": "08:15",
    "arrival_time": "12:45",
    "duration": "4h 30m",
    "departure_band": "Morning",
    "arrival_next_day": false
  },
  {
    "country": "🇯🇵 Japan",
    "arrival_city": "Fukuoka (FUK)",
    "arrival_airport": "FUK",
    "flight_number": "CX528",
    "departure_time": "09:15",
    "arrival_time": "13:45",
    "duration": "4h 30m",
    "departure_band": "Morning",
    "arrival_next_day": false
  },
  {
    "country": "🇯🇵 Japan",
    "arrival_city": "Fukuoka (FUK)",
    "arrival_airport": "FUK",
    "flight_number": "CX588",
    "departure_time": "11:00",
    "arrival_time": "15:30",
    "duration": "4h 30m",
    "departure_band": "Morning",
    "arrival_next_day": false
  },
  {
    "country": "🇯🇵 Japan",
    "arrival_city": "Sapporo (CTS)",
    "arrival_airport": "CTS",
    "flight_number": "CX580",
    "departure_time": "09:15",
    "arrival_time": "15:20",
    "duration": "6h 05m",
    "departure_band": "Morning",
    "arrival_next_day": false
  },
  {
    "country": "🇯🇵 Japan",
    "arrival_city": "Sapporo (CTS)",
    "arrival_airport": "CTS",
    "flight_number": "CX582",
    "departure_time": "10:00",
    "arrival_time": "16:05",
    "duration": "6h 05m",
    "departure_band": "Morning",
    "arrival_next_day": false
  },
  {
    "country": "🇰🇷 South Korea",
    "arrival_city": "Seoul (ICN)",
    "arrival_airport": "ICN",
    "flight_number": "CX434",
    "departure_time": "07:55",
    "arrival_time": "12:40",
    "duration": "4h 45m",
    "departure_band": "Morning",
    "arrival_next_day": false
  },
  {
    "country": "🇰🇷 South Korea",
    "arrival_city": "Seoul (ICN)",
    "arrival_airport": "ICN",
    "flight_number": "CX410",
    "departure_time": "09:25",
    "arrival_time": "14:05",
    "duration": "4h 40m",
    "departure_band": "Morning",
    "arrival_next_day": false
  },
  {
    "country": "🇰🇷 South Korea",
    "arrival_city": "Seoul (ICN)",
    "arrival_airport": "ICN",
    "flight_number": "CX418",
    "departure_time": "14:25",
    "arrival_time": "19:05",
    "duration": "4h 40m",
    "departure_band": "Afternoon",
    "arrival_next_day": false
  },
  {
    "country": "🇰🇷 South Korea",
    "arrival_city": "Seoul (ICN)",
    "arrival_airport": "ICN",
    "flight_number": "CX430",
    "departure_time": "17:40",
    "arrival_time": "22:25",
    "duration": "4h 45m",
    "departure_band": "Evening",
    "arrival_next_day": false
  },
  {
    "country": "🇰🇷 South Korea",
    "arrival_city": "Seoul (ICN)",
    "arrival_airport": "ICN",
    "flight_number": "CX426",
    "departure_time": "19:45",
    "arrival_time": "00:25",
    "duration": "4h 40m",
    "departure_band": "Evening",
    "arrival_next_day": true
  },
  {
    "country": "🇹🇼 Taiwan",
    "arrival_city": "Taipei (TPE)",
    "arrival_airport": "TPE",
    "flight_number": "CX422",
    "departure_time": "07:10",
    "arrival_time": "08:55",
    "duration": "1h 45m",
    "departure_band": "Morning",
    "arrival_next_day": false
  },
  {
    "country": "🇹🇼 Taiwan",
    "arrival_city": "Taipei (TPE)",
    "arrival_airport": "TPE",
    "flight_number": "CX488",
    "departure_time": "08:00",
    "arrival_time": "09:50",
    "duration": "1h 50m",
    "departure_band": "Morning",
    "arrival_next_day": false
  },
  {
    "country": "🇹🇼 Taiwan",
    "arrival_city": "Taipei (TPE)",
    "arrival_airport": "TPE",
    "flight_number": "CX564",
    "departure_time": "08:10",
    "arrival_time": "10:00",
    "duration": "1h 50m",
    "departure_band": "Morning",
    "arrival_next_day": false
  },
  {
    "country": "🇹🇼 Taiwan",
    "arrival_city": "Taipei (TPE)",
    "arrival_airport": "TPE",
    "flight_number": "CX530",
    "departure_time": "08:35",
    "arrival_time": "10:25",
    "duration": "1h 50m",
    "departure_band": "Morning",
    "arrival_next_day": false
  },
  {
    "country": "🇹🇼 Taiwan",
    "arrival_city": "Taipei (TPE)",
    "arrival_airport": "TPE",
    "flight_number": "CX466",
    "departure_time": "09:00",
    "arrival_time": "11:00",
    "duration": "2h 00m",
    "departure_band": "Morning",
    "arrival_next_day": false
  },
  {
    "country": "🇹🇼 Taiwan",
    "arrival_city": "Taipei (TPE)",
    "arrival_airport": "TPE",
    "flight_number": "CX450",
    "departure_time": "09:55",
    "arrival_time": "11:45",
    "duration": "1h 50m",
    "departure_band": "Morning",
    "arrival_next_day": false
  },
  {
    "country": "🇹🇼 Taiwan",
    "arrival_city": "Taipei (TPE)",
    "arrival_airport": "TPE",
    "flight_number": "CX494",
    "departure_time": "10:10",
    "arrival_time": "12:10",
    "duration": "2h 00m",
    "departure_band": "Morning",
    "arrival_next_day": false
  },
  {
    "country": "🇹🇼 Taiwan",
    "arrival_city": "Taipei (TPE)",
    "arrival_airport": "TPE",
    "flight_number": "CX400",
    "departure_time": "13:10",
    "arrival_time": "15:10",
    "duration": "2h 00m",
    "departure_band": "Afternoon",
    "arrival_next_day": false
  },
  {
    "country": "🇹🇼 Taiwan",
    "arrival_city": "Taipei (TPE)",
    "arrival_airport": "TPE",
    "flight_number": "CX420",
    "departure_time": "13:35",
    "arrival_time": "15:30",
    "duration": "1h 55m",
    "departure_band": "Afternoon",
    "arrival_next_day": false
  },
  {
    "country": "🇹🇼 Taiwan",
    "arrival_city": "Taipei (TPE)",
    "arrival_airport": "TPE",
    "flight_number": "CX472",
    "departure_time": "15:45",
    "arrival_time": "17:40",
    "duration": "1h 55m",
    "departure_band": "Afternoon",
    "arrival_next_day": false
  },
  {
    "country": "🇹🇼 Taiwan",
    "arrival_city": "Taipei (TPE)",
    "arrival_airport": "TPE",
    "flight_number": "CX402",
    "departure_time": "18:15",
    "arrival_time": "20:05",
    "duration": "1h 50m",
    "departure_band": "Evening",
    "arrival_next_day": false
  },
  {
    "country": "🇹🇼 Taiwan",
    "arrival_city": "Taipei (TPE)",
    "arrival_airport": "TPE",
    "flight_number": "CX464",
    "departure_time": "19:20",
    "arrival_time": "21:20",
    "duration": "2h 00m",
    "departure_band": "Evening",
    "arrival_next_day": false
  },
  {
    "country": "🇹🇼 Taiwan",
    "arrival_city": "Taipei (TPE)",
    "arrival_airport": "TPE",
    "flight_number": "CX408",
    "departure_time": "22:50",
    "arrival_time": "00:35",
    "duration": "1h 45m",
    "departure_band": "Night",
    "arrival_next_day": true
  },
  {
    "country": "🇹🇼 Taiwan",
    "arrival_city": "Kaohsiung (KHH)",
    "arrival_airport": "KHH",
    "flight_number": "CX432",
    "departure_time": "08:35",
    "arrival_time": "10:10",
    "duration": "1h 35m",
    "departure_band": "Morning",
    "arrival_next_day": false
  },
  {
    "country": "🇹🇼 Taiwan",
    "arrival_city": "Kaohsiung (KHH)",
    "arrival_airport": "KHH",
    "flight_number": "CX424",
    "departure_time": "11:05",
    "arrival_time": "12:40",
    "duration": "1h 35m",
    "departure_band": "Morning",
    "arrival_next_day": false
  },
  {
    "country": "🇹🇼 Taiwan",
    "arrival_city": "Kaohsiung (KHH)",
    "arrival_airport": "KHH",
    "flight_number": "CX458",
    "departure_time": "16:35",
    "arrival_time": "18:10",
    "duration": "1h 35m",
    "departure_band": "Afternoon",
    "arrival_next_day": false
  },
  {
    "country": "🇹🇼 Taiwan",
    "arrival_city": "Kaohsiung (KHH)",
    "arrival_airport": "KHH",
    "flight_number": "CX448",
    "departure_time": "21:40",
    "arrival_time": "23:10",
    "duration": "1h 30m",
    "departure_band": "Night",
    "arrival_next_day": false
  },
  {
    "country": "🇸🇬 Singapore",
    "arrival_city": "Singapore (SIN)",
    "arrival_airport": "SIN",
    "flight_number": "CX659",
    "departure_time": "01:45",
    "arrival_time": "05:30",
    "duration": "3h 45m",
    "departure_band": "Night",
    "arrival_next_day": false
  },
  {
    "country": "🇸🇬 Singapore",
    "arrival_city": "Singapore (SIN)",
    "arrival_airport": "SIN",
    "flight_number": "CX691",
    "departure_time": "08:00",
    "arrival_time": "11:45",
    "duration": "3h 45m",
    "departure_band": "Morning",
    "arrival_next_day": false
  },
  {
    "country": "🇸🇬 Singapore",
    "arrival_city": "Singapore (SIN)",
    "arrival_airport": "SIN",
    "flight_number": "CX759",
    "departure_time": "08:40",
    "arrival_time": "12:25",
    "duration": "3h 45m",
    "departure_band": "Morning",
    "arrival_next_day": false
  },
  {
    "country": "🇸🇬 Singapore",
    "arrival_city": "Singapore (SIN)",
    "arrival_airport": "SIN",
    "flight_number": "CX739",
    "departure_time": "11:15",
    "arrival_time": "15:05",
    "duration": "3h 50m",
    "departure_band": "Morning",
    "arrival_next_day": false
  },
  {
    "country": "🇸🇬 Singapore",
    "arrival_city": "Singapore (SIN)",
    "arrival_airport": "SIN",
    "flight_number": "CX791",
    "departure_time": "11:50",
    "arrival_time": "15:40",
    "duration": "3h 50m",
    "departure_band": "Morning",
    "arrival_next_day": false
  },
  {
    "country": "🇸🇬 Singapore",
    "arrival_city": "Singapore (SIN)",
    "arrival_airport": "SIN",
    "flight_number": "CX635",
    "departure_time": "15:05",
    "arrival_time": "19:05",
    "duration": "4h 00m",
    "departure_band": "Afternoon",
    "arrival_next_day": false
  },
  {
    "country": "🇸🇬 Singapore",
    "arrival_city": "Singapore (SIN)",
    "arrival_airport": "SIN",
    "flight_number": "CX711",
    "departure_time": "17:00",
    "arrival_time": "20:50",
    "duration": "3h 50m",
    "departure_band": "Evening",
    "arrival_next_day": false
  },
  {
    "country": "🇸🇬 Singapore",
    "arrival_city": "Singapore (SIN)",
    "arrival_airport": "SIN",
    "flight_number": "CX715",
    "departure_time": "20:55",
    "arrival_time": "00:45",
    "duration": "3h 50m",
    "departure_band": "Evening",
    "arrival_next_day": true
  },
  {
    "country": "🇹🇭 Thailand",
    "arrival_city": "Bangkok (BKK)",
    "arrival_airport": "BKK",
    "flight_number": "CX705",
    "departure_time": "08:00",
    "arrival_time": "10:00",
    "duration": "2h 00m",
    "departure_band": "Morning",
    "arrival_next_day": false
  },
  {
    "country": "🇹🇭 Thailand",
    "arrival_city": "Bangkok (BKK)",
    "arrival_airport": "BKK",
    "flight_number": "CX717",
    "departure_time": "09:00",
    "arrival_time": "11:05",
    "duration": "2h 05m",
    "departure_band": "Morning",
    "arrival_next_day": false
  },
  {
    "country": "🇹🇭 Thailand",
    "arrival_city": "Bangkok (BKK)",
    "arrival_airport": "BKK",
    "flight_number": "CX755",
    "departure_time": "09:25",
    "arrival_time": "11:30",
    "duration": "2h 05m",
    "departure_band": "Morning",
    "arrival_next_day": false
  },
  {
    "country": "🇹🇭 Thailand",
    "arrival_city": "Bangkok (BKK)",
    "arrival_airport": "BKK",
    "flight_number": "CX653",
    "departure_time": "12:00",
    "arrival_time": "14:00",
    "duration": "2h 00m",
    "departure_band": "Afternoon",
    "arrival_next_day": false
  },
  {
    "country": "🇹🇭 Thailand",
    "arrival_city": "Bangkok (BKK)",
    "arrival_airport": "BKK",
    "flight_number": "CX775",
    "departure_time": "13:20",
    "arrival_time": "15:25",
    "duration": "2h 05m",
    "departure_band": "Afternoon",
    "arrival_next_day": false
  },
  {
    "country": "🇹🇭 Thailand",
    "arrival_city": "Bangkok (BKK)",
    "arrival_airport": "BKK",
    "flight_number": "CX751",
    "departure_time": "14:30",
    "arrival_time": "16:30",
    "duration": "2h 00m",
    "departure_band": "Afternoon",
    "arrival_next_day": false
  },
  {
    "country": "🇹🇭 Thailand",
    "arrival_city": "Bangkok (BKK)",
    "arrival_airport": "BKK",
    "flight_number": "CX701",
    "departure_time": "16:05",
    "arrival_time": "18:00",
    "duration": "1h 55m",
    "departure_band": "Afternoon",
    "arrival_next_day": false
  },
  {
    "country": "🇹🇭 Thailand",
    "arrival_city": "Bangkok (BKK)",
    "arrival_airport": "BKK",
    "flight_number": "CX617",
    "departure_time": "22:15",
    "arrival_time": "00:10",
    "duration": "1h 55m",
    "departure_band": "Night",
    "arrival_next_day": true
  },
  {
    "country": "🇹🇭 Thailand",
    "arrival_city": "Phuket (HKT)",
    "arrival_airport": "HKT",
    "flight_number": "CX771",
    "departure_time": "08:05",
    "arrival_time": "10:50",
    "duration": "2h 45m",
    "departure_band": "Morning",
    "arrival_next_day": false
  },
  {
    "country": "🇹🇭 Thailand",
    "arrival_city": "Phuket (HKT)",
    "arrival_airport": "HKT",
    "flight_number": "CX773",
    "departure_time": "14:45",
    "arrival_time": "17:20",
    "duration": "2h 35m",
    "departure_band": "Afternoon",
    "arrival_next_day": false
  },
  {
    "country": "🇵🇭 Philippines",
    "arrival_city": "Manila (MNL)",
    "arrival_airport": "MNL",
    "flight_number": "CX907",
    "departure_time": "07:20",
    "arrival_time": "09:35",
    "duration": "2h 15m",
    "departure_band": "Morning",
    "arrival_next_day": false
  },
  {
    "country": "🇵🇭 Philippines",
    "arrival_city": "Manila (MNL)",
    "arrival_airport": "MNL",
    "flight_number": "CX901",
    "departure_time": "09:00",
    "arrival_time": "11:20",
    "duration": "2h 20m",
    "departure_band": "Morning",
    "arrival_next_day": false
  },
  {
    "country": "🇵🇭 Philippines",
    "arrival_city": "Manila (MNL)",
    "arrival_airport": "MNL",
    "flight_number": "CX919",
    "departure_time": "14:05",
    "arrival_time": "16:30",
    "duration": "2h 25m",
    "departure_band": "Afternoon",
    "arrival_next_day": false
  },
  {
    "country": "🇵🇭 Philippines",
    "arrival_city": "Manila (MNL)",
    "arrival_airport": "MNL",
    "flight_number": "CX903",
    "departure_time": "16:40",
    "arrival_time": "19:05",
    "duration": "2h 25m",
    "departure_band": "Afternoon",
    "arrival_next_day": false
  },
  {
    "country": "🇵🇭 Philippines",
    "arrival_city": "Manila (MNL)",
    "arrival_airport": "MNL",
    "flight_number": "CX913",
    "departure_time": "20:30",
    "arrival_time": "22:55",
    "duration": "2h 25m",
    "departure_band": "Evening",
    "arrival_next_day": false
  },
  {
    "country": "🇵🇭 Philippines",
    "arrival_city": "Manila (MNL)",
    "arrival_airport": "MNL",
    "flight_number": "CX939",
    "departure_time": "21:55",
    "arrival_time": "00:15",
    "duration": "2h 20m",
    "departure_band": "Night",
    "arrival_next_day": true
  },
  {
    "country": "🇵🇭 Philippines",
    "arrival_city": "Cebu (CEB)",
    "arrival_airport": "CEB",
    "flight_number": "CX921",
    "departure_time": "07:55",
    "arrival_time": "10:50",
    "duration": "2h 55m",
    "departure_band": "Morning",
    "arrival_next_day": false
  },
  {
    "country": "🇵🇭 Philippines",
    "arrival_city": "Cebu (CEB)",
    "arrival_airport": "CEB",
    "flight_number": "CX925",
    "departure_time": "15:20",
    "arrival_time": "18:10",
    "duration": "2h 50m",
    "departure_band": "Afternoon",
    "arrival_next_day": false
  },
  {
    "country": "🇻🇳 Vietnam",
    "arrival_city": "Hanoi (HAN)",
    "arrival_airport": "HAN",
    "flight_number": "CX741",
    "departure_time": "08:45",
    "arrival_time": "09:55",
    "duration": "1h 10m",
    "departure_band": "Morning",
    "arrival_next_day": false
  },
  {
    "country": "🇻🇳 Vietnam",
    "arrival_city": "Hanoi (HAN)",
    "arrival_airport": "HAN",
    "flight_number": "CX743",
    "departure_time": "16:55",
    "arrival_time": "18:10",
    "duration": "1h 15m",
    "departure_band": "Afternoon",
    "arrival_next_day": false
  },
  {
    "country": "🇻🇳 Vietnam",
    "arrival_city": "Ho Chi Minh City (SGN)",
    "arrival_airport": "SGN",
    "flight_number": "CX767",
    "departure_time": "08:20",
    "arrival_time": "10:05",
    "duration": "1h 45m",
    "departure_band": "Morning",
    "arrival_next_day": false
  },
  {
    "country": "🇻🇳 Vietnam",
    "arrival_city": "Ho Chi Minh City (SGN)",
    "arrival_airport": "SGN",
    "flight_number": "CX769",
    "departure_time": "15:35",
    "arrival_time": "17:20",
    "duration": "1h 45m",
    "departure_band": "Afternoon",
    "arrival_next_day": false
  },
  {
    "country": "🇻🇳 Vietnam",
    "arrival_city": "Ho Chi Minh City (SGN)",
    "arrival_airport": "SGN",
    "flight_number": "CX721",
    "departure_time": "22:40",
    "arrival_time": "00:20",
    "duration": "1h 40m",
    "departure_band": "Night",
    "arrival_next_day": true
  },
  {
    "country": "🇲🇾 Malaysia",
    "arrival_city": "Kuala Lumpur (KUL)",
    "arrival_airport": "KUL",
    "flight_number": "CX723",
    "departure_time": "08:10",
    "arrival_time": "12:05",
    "duration": "3h 55m",
    "departure_band": "Morning",
    "arrival_next_day": false
  },
  {
    "country": "🇲🇾 Malaysia",
    "arrival_city": "Kuala Lumpur (KUL)",
    "arrival_airport": "KUL",
    "flight_number": "CX725",
    "departure_time": "12:40",
    "arrival_time": "16:40",
    "duration": "4h 00m",
    "departure_band": "Afternoon",
    "arrival_next_day": false
  },
  {
    "country": "🇲🇾 Malaysia",
    "arrival_city": "Kuala Lumpur (KUL)",
    "arrival_airport": "KUL",
    "flight_number": "CX729",
    "departure_time": "16:55",
    "arrival_time": "20:55",
    "duration": "4h 00m",
    "departure_band": "Afternoon",
    "arrival_next_day": false
  },
  {
    "country": "🇲🇾 Malaysia",
    "arrival_city": "Kuala Lumpur (KUL)",
    "arrival_airport": "KUL",
    "flight_number": "CX733",
    "departure_time": "21:30",
    "arrival_time": "01:30",
    "duration": "4h 00m",
    "departure_band": "Night",
    "arrival_next_day": true
  },
  {
    "country": "🇲🇾 Malaysia",
    "arrival_city": "Penang (PEN)",
    "arrival_airport": "PEN",
    "flight_number": "CX633",
    "departure_time": "08:15",
    "arrival_time": "12:00",
    "duration": "3h 45m",
    "departure_band": "Morning",
    "arrival_next_day": false
  },
  {
    "country": "🇲🇾 Malaysia",
    "arrival_city": "Penang (PEN)",
    "arrival_airport": "PEN",
    "flight_number": "CX621",
    "departure_time": "15:30",
    "arrival_time": "19:10",
    "duration": "3h 40m",
    "departure_band": "Afternoon",
    "arrival_next_day": false
  },
  {
    "country": "🇮🇩 Indonesia",
    "arrival_city": "Jakarta (CGK)",
    "arrival_airport": "CGK",
    "flight_number": "CX777",
    "departure_time": "09:10",
    "arrival_time": "13:10",
    "duration": "4h 00m",
    "departure_band": "Morning",
    "arrival_next_day": false
  },
  {
    "country": "🇮🇩 Indonesia",
    "arrival_city": "Jakarta (CGK)",
    "arrival_airport": "CGK",
    "flight_number": "CX719",
    "departure_time": "15:45",
    "arrival_time": "19:40",
    "duration": "3h 55m",
    "departure_band": "Afternoon",
    "arrival_next_day": false
  },
  {
    "country": "🇮🇩 Indonesia",
    "arrival_city": "Jakarta (CGK)",
    "arrival_airport": "CGK",
    "flight_number": "CX797",
    "departure_time": "19:05",
    "arrival_time": "22:55",
    "duration": "3h 50m",
    "departure_band": "Evening",
    "arrival_next_day": false
  },
  {
    "country": "🇮🇩 Indonesia",
    "arrival_city": "Surabaya (SUB)",
    "arrival_airport": "SUB",
    "flight_number": "CX629",
    "departure_time": "14:30",
    "arrival_time": "18:15",
    "duration": "3h 45m",
    "departure_band": "Afternoon",
    "arrival_next_day": false
  },
  {
    "country": "🇮🇩 Indonesia",
    "arrival_city": "Denpasar / Bali (DPS)",
    "arrival_airport": "DPS",
    "flight_number": "CX785",
    "departure_time": "10:00",
    "arrival_time": "15:00",
    "duration": "5h 00m",
    "departure_band": "Morning",
    "arrival_next_day": false
  },
  {
    "country": "🇮🇩 Indonesia",
    "arrival_city": "Denpasar / Bali (DPS)",
    "arrival_airport": "DPS",
    "flight_number": "CX783",
    "departure_time": "12:35",
    "arrival_time": "17:40",
    "duration": "5h 05m",
    "departure_band": "Afternoon",
    "arrival_next_day": false
  },
  {
    "country": "🇰🇭 Cambodia",
    "arrival_city": "Phnom Penh (KTI)",
    "arrival_airport": "KTI",
    "flight_number": "CX607",
    "departure_time": "08:35",
    "arrival_time": "10:15",
    "duration": "1h 40m",
    "departure_band": "Morning",
    "arrival_next_day": false
  },
  {
    "country": "🇰🇭 Cambodia",
    "arrival_city": "Phnom Penh (KTI)",
    "arrival_airport": "KTI",
    "flight_number": "CX655",
    "departure_time": "15:35",
    "arrival_time": "17:15",
    "duration": "1h 40m",
    "departure_band": "Afternoon",
    "arrival_next_day": false
  },
  {
    "country": "🇮🇳 India",
    "arrival_city": "New Delhi (DEL)",
    "arrival_airport": "DEL",
    "flight_number": "CX665",
    "departure_time": "18:00",
    "arrival_time": "21:10",
    "duration": "3h 10m",
    "departure_band": "Evening",
    "arrival_next_day": false
  },
  {
    "country": "🇮🇳 India",
    "arrival_city": "New Delhi (DEL)",
    "arrival_airport": "DEL",
    "flight_number": "CX679",
    "departure_time": "20:35",
    "arrival_time": "23:50",
    "duration": "3h 15m",
    "departure_band": "Evening",
    "arrival_next_day": false
  },
  {
    "country": "🇮🇳 India",
    "arrival_city": "Mumbai (BOM)",
    "arrival_airport": "BOM",
    "flight_number": "CX683",
    "departure_time": "17:20",
    "arrival_time": "21:05",
    "duration": "3h 45m",
    "departure_band": "Evening",
    "arrival_next_day": false
  },
  {
    "country": "🇮🇳 India",
    "arrival_city": "Mumbai (BOM)",
    "arrival_airport": "BOM",
    "flight_number": "CX663",
    "departure_time": "20:35",
    "arrival_time": "00:20",
    "duration": "3h 45m",
    "departure_band": "Evening",
    "arrival_next_day": true
  },
  {
    "country": "🇮🇳 India",
    "arrival_city": "Bengaluru (BLR)",
    "arrival_airport": "BLR",
    "flight_number": "CX623",
    "departure_time": "20:55",
    "arrival_time": "00:10",
    "duration": "3h 15m",
    "departure_band": "Evening",
    "arrival_next_day": true
  },
  {
    "country": "🇮🇳 India",
    "arrival_city": "Chennai (MAA)",
    "arrival_airport": "MAA",
    "flight_number": "CX651",
    "departure_time": "20:35",
    "arrival_time": "23:35",
    "duration": "3h 00m",
    "departure_band": "Evening",
    "arrival_next_day": false
  },
  {
    "country": "🇮🇳 India",
    "arrival_city": "Hyderabad (HYD)",
    "arrival_airport": "HYD",
    "flight_number": "CX673",
    "departure_time": "22:30",
    "arrival_time": "01:35",
    "duration": "3h 05m",
    "departure_band": "Night",
    "arrival_next_day": true
  },
  {
    "country": "🇳🇵 Nepal",
    "arrival_city": "Kathmandu (KTM)",
    "arrival_airport": "KTM",
    "flight_number": "CX603",
    "departure_time": "18:55",
    "arrival_time": "21:45",
    "duration": "2h 50m",
    "departure_band": "Evening",
    "arrival_next_day": false
  },
  {
    "country": "🇱🇰 Sri Lanka",
    "arrival_city": "Colombo (CMB)",
    "arrival_airport": "CMB",
    "flight_number": "CX611",
    "departure_time": "20:35",
    "arrival_time": "23:30",
    "duration": "2h 55m",
    "departure_band": "Evening",
    "arrival_next_day": false
  },
  {
    "country": "🇧🇩 Bangladesh",
    "arrival_city": "Dhaka (DAC)",
    "arrival_airport": "DAC",
    "flight_number": "CX667",
    "departure_time": "22:55",
    "arrival_time": "01:00",
    "duration": "2h 05m",
    "departure_band": "Night",
    "arrival_next_day": true
  }
]